onthefly/__init__.py
onthefly/checkpoints.py
onthefly/ckpt_utils.py
onthefly/config.py
onthefly/control.py
onthefly/dashboard_channel.py
onthefly/data_explorer.py
onthefly/device_utils.py
onthefly/factory.py
onthefly/ids.py
onthefly/kmeans_utils.py
onthefly/merging.py
onthefly/metrics_utils.py
onthefly/runtime_metrics.py
onthefly/sampler_utils.py
onthefly/scale.py
onthefly/trainer.py
onthefly/utils.py
onthefly/mixins/checkpoint_mixin.py
onthefly/mixins/commands_mixin.py
onthefly/mixins/events_mixin.py
onthefly/mixins/feature_mixin.py
onthefly/mixins/run_management_mixin.py
onthefly/mixins/train_mixin.py
onthefly/session/__init__.py
onthefly/session/base.py
onthefly/session/external.py
onthefly/session/native.py
onthefly/wrappers/base.py
onthefly/wrappers/lightning.py
onthefly_ai-0.1.4.dist-info/LICENSE.TXT
onthefly_ai-0.1.4.dist-info/METADATA
onthefly_ai-0.1.4.dist-info/WHEEL
onthefly_ai-0.1.4.dist-info/top_level.txt
onthefly_ai-0.1.4.dist-info/RECORD
