Metadata-Version: 2.1
Name: onthefly-ai
Version: 0.1.4
Summary: Interactive ML Development in VS Code.
Author-email: Luke Skertich <klukeskertich@gmail.com>
License: MIT
Requires-Python: >=3.9
License-File: LICENSE.TXT
Requires-Dist: torch >=2.0.0
Requires-Dist: numpy >=1.23
Requires-Dist: scipy >=1.10
Requires-Dist: psutil >=5.9
Provides-Extra: dev
Requires-Dist: ipython ; extra == 'dev'
Requires-Dist: pytest ; extra == 'dev'
Requires-Dist: ruff ; extra == 'dev'
Requires-Dist: mypy ; extra == 'dev'
Requires-Dist: build ; extra == 'dev'
Requires-Dist: twine ; extra == 'dev'
Provides-Extra: explorer
Requires-Dist: scikit-learn >=1.3 ; extra == 'explorer'
Requires-Dist: umap-learn >=0.5 ; extra == 'explorer'
Requires-Dist: pandas >=2.0 ; extra == 'explorer'
Provides-Extra: lightning
Requires-Dist: lightning >=2.2.0 ; extra == 'lightning'
Provides-Extra: metrics
Requires-Dist: pynvml >=11.5 ; extra == 'metrics'
